<?xml version="1.0" encoding="utf-8"?>
<l10n>
    <texts>
        <text name="input_WT_INTERACT"       text="Dienst beginnen/beeindigen"/>
        <text name="wt_input_interact"       text="[E] Interactie met werkplek"/>
        <text name="wt_input_start_shift"    text="[E] Dienst beginnen bij %s"/>
        <text name="wt_input_end_shift"      text="[E] Dienst beeindigen bij %s"/>
        <text name="wt_hud_on_shift"         text="AAN HET WERK"/>
        <text name="wt_hud_location"         text="Locatie:"/>
        <text name="wt_hud_time"             text="Tijd:"/>
        <text name="wt_hud_earned"           text="Verdiend:"/>
        <text name="wt_hud_shift_started"    text="Dienst begonnen bij %s\n$%d/uur"/>
        <text name="wt_hud_shift_ended"      text="Dienst beeindigd\n+$%d verdiend"/>
        <text name="wt_store_name"           text="Werkplek trigger zone"/>
        <text name="wt_store_desc"           text="Plaatsbaar overal. Loop de zone in en druk [E] om je dienst te beginnen en inkomen te verdienen."/>
        <text name="wt_store_function"       text="Wijst een plaatsbare werklocatie aan met instelbare naam en uurloon"/>
        <text name="wt_notify_shift_started" text="Dienst begonnen bij '%s'"/>
        <text name="wt_notify_shift_ended"   text="Dienst beeindigd - $%d verdiend"/>
        <text name="wt_notify_left_trigger"  text="Je hebt de werkzone verlaten - dienst beeindigd"/>
        <!-- Help Line category titles -->
        <text name="helpLine_wt_cat_overview"  text="Overzicht"/>
        <text name="helpLine_wt_cat_setup"     text="Aan de slag"/>
        <text name="helpLine_wt_cat_shift"     text="Een dienst werken"/>
        <text name="helpLine_wt_cat_manage"    text="Werkplekken beheren"/>
        <text name="helpLine_wt_cat_hud"       text="HUD en instellingen"/>
        <text name="helpLine_wt_cat_tips"      text="Tips en multiplayer"/>
        <text name="helpLine_wt_cat_about"     text="Over en credits"/>
    </texts>
</l10n>
